Metadata-Version: 2.1
Name: quitaracentos
Version: 0.0.2
Summary: Remove spanish accents from strings (except ñ)
Author: FerdinandoPH
Author-email: perez.holguin@gmail.com
License-File: license.txt
